grpctunnel/__init__.py
grpctunnel/client.py
grpctunnel/context.py
grpctunnel/flow_control.py
grpctunnel/handler.py
grpctunnel/interceptors.py
grpctunnel/metadata.py
grpctunnel/options.py
grpctunnel/py.typed
grpctunnel/reverse.py
grpctunnel/reverse_channel.py
grpctunnel/server.py
grpctunnel/proto/__init__.py
grpctunnel/proto/v1/__init__.py
grpctunnel/proto/v1/tunnel_pb2.py
grpctunnel/proto/v1/tunnel_pb2.pyi
grpctunnel/proto/v1/tunnel_pb2_grpc.py
grpctunnel_py-0.3.0.dist-info/METADATA
grpctunnel_py-0.3.0.dist-info/WHEEL
grpctunnel_py-0.3.0.dist-info/licenses/LICENSE
grpctunnel_py-0.3.0.dist-info/RECORD
