Metadata-Version: 2.4
Name: grpctunnel-py
Version: 0.3.0
Summary: Python port of grpctunnel - carry gRPC over gRPC
Project-URL: Homepage, https://github.com/dvaldivia/grpctunnel-py
Project-URL: Repository, https://github.com/dvaldivia/grpctunnel-py
Project-URL: Documentation, https://github.com/dvaldivia/grpctunnel-py/blob/main/README.md
Project-URL: Original Go Implementation, https://github.com/jhump/grpctunnel
Author: Daniel Valdivia
License: Apache-2.0
License-File: LICENSE
Keywords: grpc,reverse-tunnel,rpc,tunnel
Classifier: Development Status :: 4 - Beta
Classifier: Intended Audience :: Developers
Classifier: License :: OSI Approved :: Apache Software License
Classifier: Programming Language :: Python :: 3
Classifier: Programming Language :: Python :: 3.11
Classifier: Programming Language :: Python :: 3.12
Classifier: Programming Language :: Python :: 3.13
Classifier: Topic :: Software Development :: Libraries :: Python Modules
Classifier: Topic :: System :: Networking
Requires-Python: >=3.11
Requires-Dist: googleapis-common-protos>=1.72.0
Requires-Dist: grpcio-tools>=1.76.0
Requires-Dist: grpcio>=1.76.0
Requires-Dist: protobuf>=6.33.2
